{
  "label_map": {
    "0": "NORMAL",
    "1": "MISLEADING",
    "2": "MISLEADING",
    "3": "MISLEADING",
    "4": "MISLEADING",
    "5": "MISLEADING",
    "6": "OBSTRUCTING",
    "7": "OBSTRUCTING",
    "8": "OBSTRUCTING",
    "9": "OBSTRUCTING",
    "10": "PRESSURING",
    "11": "PRESSURING",
    "12": "PRESSURING",
    "13": "PRESSURING",
    "14": "PRESSURING",
    "15": "EXPLOITING"
  },
  "category_map": {
    "0": 0,
    "1": 1,
    "2": 1,
    "3": 1,
    "4": 1,
    "5": 1,
    "6": 2,
    "7": 2,
    "8": 2,
    "9": 2,
    "10": 3,
    "11": 3,
    "12": 3,
    "13": 3,
    "14": 3,
    "15": 4
  },
  "category_names": [
    "NORMAL",
    "MISLEADING",
    "OBSTRUCTING",
    "PRESSURING",
    "EXPLOITING"
  ],
  "detail_names": {
    "0": "정상",
    "1": "설명절차축약",
    "2": "속임수질문",
    "3": "잘못된계층",
    "4": "사전선택",
    "5": "허위광고",
    "6": "해지방해",
    "7": "숨긴정보",
    "8": "가격비교방해",
    "9": "클릭피로",
    "10": "기습광고",
    "11": "반복간섭",
    "12": "감정언어",
    "13": "감각조작",
    "14": "활동알림",
    "15": "순차가격"
  },
  "train_size": 1880,
  "test_size": 160,
  "feature_dim": 1280,
  "clip_model": "ViT-B-32/laion2b_s34b_b79k",
  "bert_model": "bert-base-multilingual-cased",
  "cv_f1_category": 0.4538371137916524,
  "cv_f1_detail": 0.21607432708579183
}